kwix/__init__.py
kwix/_modidx.py
kwix/mixs.py
kwix/test.py
kwix/utils.py
kwix-0.0.5.dist-info/LICENSE
kwix-0.0.5.dist-info/METADATA
kwix-0.0.5.dist-info/WHEEL
kwix-0.0.5.dist-info/entry_points.txt
kwix-0.0.5.dist-info/top_level.txt
kwix-0.0.5.dist-info/RECORD
